lotr_sdk/__init__.py
lotr_sdk/movie.py
lotr_sdk/utils/__init__.py
lotr_sdk/utils/logger.py
isaac_lotr_sdk-0.0.2.dist-info/LICENSE
isaac_lotr_sdk-0.0.2.dist-info/METADATA
isaac_lotr_sdk-0.0.2.dist-info/WHEEL
isaac_lotr_sdk-0.0.2.dist-info/RECORD
