Metadata-Version: 2.1
Name: isaac-lotr-sdk
Version: 0.0.2
Summary: SDK Implementing https://the-one-api.dev API to serve information on all LOTR lore.
License: MIT
Author: Isaac Aderonmu
Author-email: aderonmuisaac@gmail.com
Requires-Python: >=3.8,<4.0
Classifier: License :: OSI Approved :: MIT License
Classifier: Programming Language :: Python :: 3
Classifier: Programming Language :: Python :: 3.8
Classifier: Programming Language :: Python :: 3.9
Classifier: Programming Language :: Python :: 3.10
Classifier: Programming Language :: Python :: 3.11
Requires-Dist: requests (>=2.28.2,<3.0.0)
